d1_gmn/__init__.py
d1_gmn/manage.py
d1_gmn/settings_template.py
d1_gmn/settings_test.py
d1_gmn/version.py
d1_gmn/wsgi.py
d1_gmn/app/__init__.py
d1_gmn/app/auth.py
d1_gmn/app/context_processors.py
d1_gmn/app/db_filter.py
d1_gmn/app/delete.py
d1_gmn/app/did.py
d1_gmn/app/event_log.py
d1_gmn/app/gmn.py
d1_gmn/app/local_replica.py
d1_gmn/app/mgmt_base.py
d1_gmn/app/model_util.py
d1_gmn/app/models.py
d1_gmn/app/node.py
d1_gmn/app/node_registry.py
d1_gmn/app/object_format_cache.py
d1_gmn/app/proxy.py
d1_gmn/app/psycopg_adapter.py
d1_gmn/app/resource_map.py
d1_gmn/app/revision.py
d1_gmn/app/scimeta.py
d1_gmn/app/sciobj_store.py
d1_gmn/app/settings_default.py
d1_gmn/app/subject.py
d1_gmn/app/sysmeta.py
d1_gmn/app/sysmeta_extract.py
d1_gmn/app/urls.py
d1_gmn/app/util.py
d1_gmn/app/management/__init__.py
d1_gmn/app/management/commands/__init__.py
d1_gmn/app/management/commands/audit-proxy-sciobj.py
d1_gmn/app/management/commands/audit-sync-cn-to-mn.py
d1_gmn/app/management/commands/audit-sync-mn-to-cn.py
d1_gmn/app/management/commands/diag-cleardb.py
d1_gmn/app/management/commands/diag-proxy-set-url.py
d1_gmn/app/management/commands/diag-resource-map.py
d1_gmn/app/management/commands/diag-restore-sciobj.py
d1_gmn/app/management/commands/diag-revision-chains.py
d1_gmn/app/management/commands/diag-sysmeta-update.py
d1_gmn/app/management/commands/export-sysmeta-fields.py
d1_gmn/app/management/commands/get-sciobj-location.py
d1_gmn/app/management/commands/import.py
d1_gmn/app/management/commands/node-register.py
d1_gmn/app/management/commands/node-update.py
d1_gmn/app/management/commands/node-view.py
d1_gmn/app/management/commands/process_refresh_queue.py
d1_gmn/app/management/commands/process_replication_queue.py
d1_gmn/app/management/commands/view-cert.py
d1_gmn/app/management/commands/view-event-log.py
d1_gmn/app/management/commands/view-jwt.py
d1_gmn/app/management/commands/view-object-info.py
d1_gmn/app/management/commands/view-status.py
dataone.gmn-3.5.2.dist-info/METADATA
dataone.gmn-3.5.2.dist-info/WHEEL
dataone.gmn-3.5.2.dist-info/entry_points.txt
dataone.gmn-3.5.2.dist-info/top_level.txt
dataone.gmn-3.5.2.dist-info/RECORD
