Metadata-Version: 2.1
Name: dataone.gmn
Version: 3.5.2
Summary: DataONE Generic Member Node (GMN)
Home-page: https://github.com/DataONEorg/d1_python
Author: DataONE Project
Author-email: developers@dataone.org
License: Apache License, Version 2.0
Keywords: DataONE server member-node coordinating-node
Classifier: Development Status :: 5 - Production/Stable
Classifier: Intended Audience :: Developers
Classifier: Topic :: Scientific/Engineering
Classifier: License :: OSI Approved :: Apache Software License
Classifier: Programming Language :: Python :: 3
Classifier: Programming Language :: Python :: 3.7
Requires-Dist: dataone.cli (>=3.5.2)
Requires-Dist: dataone.common (>=3.5.2)
Requires-Dist: dataone.libclient (>=3.5.2)
Requires-Dist: dataone.scimeta (>=3.5.2)
Requires-Dist: django (>=4.2.1)
Requires-Dist: iso8601 (>=1.1.0)
Requires-Dist: psycopg2-binary (>=2.9.6)
Requires-Dist: PyJWT (>=2.7.0)
Requires-Dist: pyxb-x (>=1.2.6.1)
Requires-Dist: requests (>=2.31.0)
